{
  "_aiGenerated": true,
  "_generatedAt": "2026-06-22T08:06:47.075Z",
  "_model": "dify:采购诊断(App1)+经营洞察(App2)",
  "_app2Generated": true,
  "anomalyCards": {
    "connector::高速背板连接器::供应商A": {
      "riskLevel": "high",
      "title": "高速背板连接器 · 供应商A",
      "conclusion": "高速背板连接器供应商A本次采购价环比上涨14.3%，而同期铜价下跌3.8%，成本与价格背离达18.1个百分点，且报价高于同行11.3%，属于严重异常。",
      "attribution": "供应商A趁原材料下行之机大幅提价，且供应集中度高达0.6，存在利用单一货源优势抬价的行为，不排除内部价格管控缺失或供应商串通风险。",
      "suggestions": [
        "立即暂停该供应商新订单，启动价格回溯与谈判，要求其提供最新成本构成证明",
        "引入二供或开发替代供应商，将供应集中度降至0.4以下",
        "对近半年所有品类价格进行全量复盘，检查是否存在类似背离",
        "将该品类纳入下季度招标清单，用市场竞价倒逼供应商回调价格"
      ],
      "notify": [
        "采购部负责人",
        "分管副总",
        "供应链风控",
        "财务"
      ],
      "confidence": 0.92,
      "aiGenerated": true
    },
    "pcb::高频高速板::供应商B": {
      "riskLevel": "mid",
      "title": "高频高速板 · 供应商B",
      "conclusion": "供应商B的集中度高达82%，其高频高速板价格环比仅上涨2.0%，但覆铜板CCL材料成本飙升18.6%，量价背离达-16.7个百分点，且同行价差为-24.6%，存在单一依赖风险与传导滞后。",
      "attribution": "根因系供应商集中度过高，供应商B在材料成本大幅上涨背景下，价格调整严重滞后，采购方议价被动；同时该供应商可能通过压缩利润或转移成本维持供货，长期存在断供或质量下降隐患。",
      "suggestions": [
        "立即启动第二货源认证，1个月内至少引入1家合格替代供应商，将集中度降到60%以下",
        "与供应商B开展价格回溯谈判，要求解释量价背离，争取按材料涨幅补回价差或签订季度调价协议",
        "对高频高速板启动战略备货，锁定当前价位，应对供应商可能单方面提价或限供",
        "财务部门复核供应商B成本结构，评估其持续供货能力，并暂缓对其新增订单的预付比例"
      ],
      "notify": [
        "采购部负责人",
        "供应链风控",
        "分管副总"
      ],
      "confidence": 0.75,
      "aiGenerated": true
    }
  },
  "presetAnswers": {
    "biggestRisk": "连接器产品线的高速背板连接器由供应商A独家供应60%，价格高于同行18.1%，且出现环比异动，若持续将直接侵蚀利润，存在供应与成本双重失控风险。",
    "costPressure": "连接器产品线成本压力最大，主要源于议价问题，其高速背板连接器价格明显高于同行，并非材料普涨驱动；PCB产品线虽集中度高但当前价格低于同行，暂未构成成本压力。",
    "savingOpp": "连接器产品线存在显著降本机会，通过价格谈判将高速背板连接器价格拉回至同行水平，可直接节省约5%-10%的采购支出，对应量级约64-128万元。"
  },
  "execActions": [
    "立即启动对供应商A的专项价格谈判，要求其报价回归行业基准，目标单价降幅不低于15%，预期可年化降低连接器采购成本约192万元。",
    "半年内为供应商A开发至少一家替代供应商，将集中度从60%降至40%以下，降低断供风险并增强议价筹码，同时保障供应链韧性。",
    "将PCB供应商B的集中度82%纳入季度风险评估，要求采购团队在Q2前完成第二供应商认证，确保在高频高速板需求波动时具备快速切换能力，避免未来被动涨价。"
  ]
}
